kawapythonserver/__init__.py
kawapythonserver/script_runner.py
kawapythonserver/scripts/__init__.py
kawapythonserver/scripts/kawa_secrets.py
kawapythonserver/scripts/kawa_tool.py
kawapythonserver/scripts/kawa_tool_kit.py
kawapythonserver/scripts/metadata_checker.py
kawapythonserver/scripts/name_with_type.py
kawapythonserver/scripts/name_with_type_with_dataframe.py
kawapythonserver/scripts/processors/__init__.py
kawapythonserver/scripts/processors/kawa_action_processor.py
kawapythonserver/scripts/processors/kawa_python_automation_processor.py
kawapythonserver/scripts/processors/kawa_python_column_processor.py
kawapythonserver/scripts/processors/kawa_python_datasource_preview_processor.py
kawapythonserver/scripts/processors/kawa_python_datasource_processor.py
kawapythonserver/scripts/processors/kawa_python_metadata_processor.py
kawapythonserver/scripts/processors/kawa_python_runnable_processor.py
kawapythonserver/scripts/processors/kawa_python_script_with_json_output_processor.py
kawapythonserver/scripts/processors/kawa_python_workflow_processor.py
kawapythonserver/server/__init__.py
kawapythonserver/server/aes_cipher.py
kawapythonserver/server/clear_script_with_secrets.py
kawapythonserver/server/git_repository.py
kawapythonserver/server/interpreter_error.py
kawapythonserver/server/kawa_directory_manager.py
kawapythonserver/server/kawa_error_manager.py
kawapythonserver/server/kawa_flight_server.py
kawapythonserver/server/kawa_log_manager.py
kawapythonserver/server/kawa_metadata.py
kawapythonserver/server/kawa_pex_builder.py
kawapythonserver/server/kawa_script_runner_inputs.py
kawapythonserver/server/start_flight_server.py
kawapythonserver/server/jobs/__init__.py
kawapythonserver/server/jobs/job_executor.py
kawapythonserver/server/jobs/job_executor_2.py
kawapythonserver/server/jobs/job_manager_client.py
kawapythonserver/server/jobs/job_runner.py
kawapythonserver/test/__init__.py
kawapythonserver/test/test_meta_data_checker.py
kawapythonserver-0.33.27.dist-info/METADATA
kawapythonserver-0.33.27.dist-info/WHEEL
kawapythonserver-0.33.27.dist-info/entry_points.txt
kawapythonserver-0.33.27.dist-info/top_level.txt
kawapythonserver-0.33.27.dist-info/RECORD
