Metadata-Version: 2.4
Name: kawapythonserver
Version: 0.33.27
Summary: Kawa python server to run python scripts from Kawa - https://learn.kawa.ai
Author-email: Kawa Analytics <emmmanuel@kawa.ai>, Kawa Analytics <greg@kawa.ai>, Kawa Analytics <max@kawa.ai>
Maintainer-email: Kawa Analytics <max@kawa.ai>, Kawa Analytics <greg@kawa.ai>, Kawa Analytics <emmmanuel@kawa.ai>
Requires-Python: >=3.10
Requires-Dist: kywy>=0.32.6
Requires-Dist: pandas
Requires-Dist: pyarrow==16.1.0
Requires-Dist: python-dotenv>=1.0.0
Requires-Dist: pex==2.33.1
Requires-Dist: cachetools==5.3.3
Requires-Dist: filelock==3.18.0
Requires-Dist: importlib_metadata==8.6.1
